multi_agents/__init__.py
multi_agents/agents_graph.py
multi_agents/chief.py
multi_agents/editor.py
multi_agents/main.py
multi_agents/memory_draft.py
multi_agents/memory_research.py
multi_agents/publisher.py
multi_agents/researcher.py
multi_agents/reviewer.py
multi_agents/reviser.py
multi_agents/writer.py
multi_agents/utils/__init__.py
multi_agents/utils/file_formats.py
multi_agents/utils/llms.py
multi_agents/utils/views.py
sz_researcher/__init__.py
sz_researcher/config/__init__.py
sz_researcher/config/config.py
sz_researcher/context/__init__.py
sz_researcher/context/compression.py
sz_researcher/context/retriever.py
sz_researcher/document/__init__.py
sz_researcher/document/document.py
sz_researcher/llm_provider/__init__.py
sz_researcher/llm_provider/anthropic/__init__.py
sz_researcher/llm_provider/anthropic/anthropic.py
sz_researcher/llm_provider/google/__init__.py
sz_researcher/llm_provider/google/google.py
sz_researcher/llm_provider/groq/__init__.py
sz_researcher/llm_provider/groq/groq.py
sz_researcher/llm_provider/huggingface/__init__.py
sz_researcher/llm_provider/huggingface/huggingface.py
sz_researcher/llm_provider/mistral/__init__.py
sz_researcher/llm_provider/mistral/mistral.py
sz_researcher/llm_provider/ollama/__init__.py
sz_researcher/llm_provider/ollama/ollama.py
sz_researcher/llm_provider/openai/__init__.py
sz_researcher/llm_provider/openai/openai.py
sz_researcher/master/__init__.py
sz_researcher/master/actions.py
sz_researcher/master/agent.py
sz_researcher/master/prompts.py
sz_researcher/memory/__init__.py
sz_researcher/memory/embeddings.py
sz_researcher/retrievers/__init__.py
sz_researcher/retrievers/bing/__init__.py
sz_researcher/retrievers/bing/bing.py
sz_researcher/retrievers/custom/__init__.py
sz_researcher/retrievers/custom/custom.py
sz_researcher/retrievers/duckduckgo/__init__.py
sz_researcher/retrievers/duckduckgo/duckduckgo.py
sz_researcher/retrievers/google/__init__.py
sz_researcher/retrievers/google/google.py
sz_researcher/scraper/__init__.py
sz_researcher-0.7.5.dist-info/LICENSE
sz_researcher-0.7.5.dist-info/METADATA
sz_researcher-0.7.5.dist-info/WHEEL
sz_researcher-0.7.5.dist-info/top_level.txt
sz_researcher-0.7.5.dist-info/RECORD
