Metadata-Version: 2.1
Name: sz-researcher
Version: 0.7.5
Summary: sz-researcher是一款为中文研究而设计的自主智能体，适用于多种任务。
Home-page: https://github.com/yiouyou/sz-researcher
Author: Zack Song
Author-email: zhuosong@gmail.com
License: MIT
Classifier: License :: OSI Approved :: MIT License
Classifier: Intended Audience :: Developers
Classifier: Intended Audience :: Education
Classifier: Intended Audience :: Science/Research
Classifier: Programming Language :: Python :: 3.11
Classifier: Programming Language :: Python :: 3.12
Classifier: Topic :: Scientific/Engineering :: Artificial Intelligence
License-File: LICENSE
Requires-Dist: beautifulsoup4
Requires-Dist: colorama
Requires-Dist: duckduckgo-search ==5.3.1b1
Requires-Dist: md2pdf
Requires-Dist: playwright
Requires-Dist: openai
Requires-Dist: python-dotenv
Requires-Dist: pyyaml
Requires-Dist: pydantic
Requires-Dist: python-multipart
Requires-Dist: markdown
Requires-Dist: langchain <0.3,>=0.2
Requires-Dist: langchain-community <0.3,>=0.2
Requires-Dist: langchain-openai <0.2,>=0.1
Requires-Dist: langchain-google-genai <2,>=1
Requires-Dist: langchain-groq <0.2,>=0.1
Requires-Dist: langchain-anthropic <0.2,>=0.1
Requires-Dist: langchain-mistralai <0.2,>=0.1
Requires-Dist: langchain-huggingface <0.1,>=0.0.1
Requires-Dist: langchain-together <0.2,>=0.1
Requires-Dist: langchain-cohere
Requires-Dist: langchain-google-vertexai
Requires-Dist: langchain-fireworks
Requires-Dist: langchain-aws
Requires-Dist: tiktoken
Requires-Dist: tavily-python
Requires-Dist: arxiv
Requires-Dist: PyMuPDF
Requires-Dist: requests
Requires-Dist: aiofiles
Requires-Dist: newspaper3k
Requires-Dist: SQLAlchemy
Requires-Dist: mistune
Requires-Dist: python-docx
Requires-Dist: htmldocx
Requires-Dist: lxml[html_clean]
Requires-Dist: websockets
Requires-Dist: unstructured
Requires-Dist: pandas
Requires-Dist: json-repair
